[
  {
    "timestamp": 1583758903590.7942,
    "exceptionDetails": {
      "exceptionId": 1,
      "text": "Uncaught",
      "lineNumber": 80,
      "columnNumber": 10,
      "scriptId": "32",
      "url": "https://housing.temple.edu/temple-towers",
      "exception": {
        "type": "object",
        "subtype": "error",
        "className": "SyntaxError",
        "description": "SyntaxError: Unexpected token ')'",
        "objectId": "{\"injectedScriptId\":3,\"id\":1}",
        "preview": {
          "type": "object",
          "subtype": "error",
          "description": "SyntaxError: Unexpected token ')'",
          "overflow": false,
          "properties": [
            {
              "name": "stack",
              "type": "string",
              "value": "SyntaxError: Unexpected token ')'"
            },
            {
              "name": "message",
              "type": "string",
              "value": "Unexpected token ')'"
            }
          ]
        }
      },
      "executionContextId": 3
    }
  }
]